PlotRunner/__init__.py
PlotRunner/builder.py
PlotRunner/factory.py
PlotRunner/runner.py
PlotRunnerMT-0.1.1.dist-info/DESCRIPTION.rst
PlotRunnerMT-0.1.1.dist-info/METADATA
PlotRunnerMT-0.1.1.dist-info/RECORD
PlotRunnerMT-0.1.1.dist-info/WHEEL
PlotRunnerMT-0.1.1.dist-info/metadata.json
PlotRunnerMT-0.1.1.dist-info/top_level.txt
