Metadata-Version: 2.0
Name: PlotRunnerMT
Version: 0.1.1
Summary: a package of drawing intervative graph
Home-page: UNKNOWN
Author: ki
Author-email: max_and_min@163.com
License: MIT
Platform: UNKNOWN
